weatherquery/__init__.py
weatherquery/consts.py
weatherquery/core.py
weatherquery/getapi.py
weatherquery/name2code.py
weatherquery/py.typed
weatherquery/utils.py
weatherquery-0.1.4.dist-info/licenses/LICENSE
weatherquery-0.1.4.dist-info/METADATA
weatherquery-0.1.4.dist-info/WHEEL
weatherquery-0.1.4.dist-info/top_level.txt
weatherquery-0.1.4.dist-info/RECORD
