Metadata-Version: 2.4
Name: weatherquery
Version: 0.1.4
Summary: 这是一个轻量级的快捷的天气查询Python库
Author-email: xiatianxuan <xiatianxuan2025@163.com>, fexcode <2734664632@qq.com>
Requires-Python: >=3.10
License-File: LICENSE
Dynamic: license-file
